notifykit/__init__.py
notifykit/client.py
notifykit/py.typed
notifykitdev-1.0.0.dist-info/METADATA
notifykitdev-1.0.0.dist-info/WHEEL
notifykitdev-1.0.0.dist-info/RECORD
