Metadata-Version: 2.4
Name: notifykitdev
Version: 1.0.0
Summary: Official NotifyKit SDK for Python - Send notifications from your apps
Project-URL: Homepage, https://notifykit.dev
Project-URL: Documentation, https://notifykit.dev/docs
Project-URL: Repository, https://github.com/notifykit/notifykit-python
Project-URL: Issues, https://github.com/notifykit/notifykit-python/issues
Author-email: NotifyKit <support@notifykit.dev>
License: MIT
Keywords: alerts,notifications,notifykit,push,sdk,telegram
Classifier: Development Status :: 5 - Production/Stable
Classifier: Intended Audience :: Developers
Classifier: License :: OSI Approved :: MIT License
Classifier: Operating System :: OS Independent
Classifier: Programming Language :: Python :: 3
Classifier: Programming Language :: Python :: 3.8
Classifier: Programming Language :: Python :: 3.9
Classifier: Programming Language :: Python :: 3.10
Classifier: Programming Language :: Python :: 3.11
Classifier: Programming Language :: Python :: 3.12
Classifier: Topic :: Communications
Classifier: Topic :: Software Development :: Libraries :: Python Modules
Classifier: Typing :: Typed
Requires-Python: >=3.8
Requires-Dist: httpx>=0.24.0
